pyrome/__init__.py
pyrome/contents.py
pyrome/download.py
pyrome/parser.py
pyrome/rome.py
pyrome/schema.py
pyrome-0.1.1.dist-info/DESCRIPTION.rst
pyrome-0.1.1.dist-info/METADATA
pyrome-0.1.1.dist-info/RECORD
pyrome-0.1.1.dist-info/WHEEL
pyrome-0.1.1.dist-info/metadata.json
pyrome-0.1.1.dist-info/top_level.txt
