Metadata-Version: 2.0
Name: pyrome
Version: 0.1.1
Summary: Load Pole Emploie ROME into a database and offers utilities
Home-page: https://github.com/jurismarches/pyrome
Author: Jurismarches
Author-email: contact@jurismarches.com
License: UNKNOWN
Platform: UNKNOWN
Classifier: Development Status :: 3 - Alpha
Classifier: License :: OSI Approved :: GNU Lesser General Public License v3 or later (LGPLv3+)
Classifier: Intended Audience :: Developers
Classifier: Programming Language :: Python
Classifier: Programming Language :: Python :: 3.4
Classifier: Natural Language :: French
Requires-Dist: peewee (>=2.9.1)
